torrentstream/__init__.py
torrentstream/torrent.py
torrentstream-0.3.1.dist-info/entry_points.txt
torrentstream-0.3.1.dist-info/WHEEL
torrentstream-0.3.1.dist-info/METADATA
torrentstream-0.3.1.dist-info/RECORD
