Metadata-Version: 2.1
Name: torrentstream
Version: 0.3.1
Summary: Quick n' dirty torrent streaming with libtorrent and python
License: Apache-2.0
Author: David Francos
Author-email: opensource@davidfrancos.net
Requires-Python: >=3.8,<4.0
Classifier: License :: OSI Approved :: Apache Software License
Classifier: Programming Language :: Python :: 3
Classifier: Programming Language :: Python :: 3.8
Classifier: Programming Language :: Python :: 3.9
Requires-Dist: async_timeout (>=3.0.1,<4.0.0)
Requires-Dist: python-libtorrent-bin (>=2.0.2,<3.0.0)
Requires-Dist: rich (>=9.2.0,<10.0.0)
